pyqueue_test/__init__.py
pyqueue_test/pyqueue.py
pyqueue_test/exceptions/Exceptions.py
pyqueue_test/exceptions/__init__.py
pyqueue_test-0.0.1.dist-info/METADATA
pyqueue_test-0.0.1.dist-info/WHEEL
pyqueue_test-0.0.1.dist-info/top_level.txt
pyqueue_test-0.0.1.dist-info/RECORD
