Metadata-Version: 2.1
Name: pyqueue_test
Version: 0.0.1
Summary: Test to make my own queue class
Author: Torak Schoorens/enigma_ZER0
Author-email: torak.schoorens@gmail.com
Keywords: python3,first package,experiment
Classifier: Development Status :: 1 - Planning
Classifier: Intended Audience :: Other Audience
Classifier: Programming Language :: Python :: 3
Classifier: Operating System :: OS Independent
